code/verilog/3/out_n_clock/out_n_clock-2.v
module out_n_clock(
    out,
    clock, reset_
);
    output out;
    input clock, reset_;

    reg OUT;
    assign out = OUT;

    localparam N = 3;
    reg [3:0] COUNT;

    reg STAR;
    localparam S0 = 0, S1 = 1;

    always @(reset_ == 0) begin
        COUNT <= N;
        OUT <= 0;
        STAR <= S0;
    end

    wire [3:0] next_count_s0;
    assign #2 next_count_s0 = COUNT - 1;

    wire next_star_s0;
    assign #2 next_star_s0 = (COUNT == 1) ? S1 : S0;
    
    always @(posedge clock) if (reset_ == 1) #3 begin
        casex (STAR)
            S0: begin
                COUNT <= next_count_s0;
                OUT <= 1;
                STAR <= next_star_s0;
            end

            S1: begin
                COUNT <= N;
                OUT <= 0;
                STAR <= S0;
            end
        endcase
    end
endmodule

code/verilog/3/out_n_clock/testbench.v
module testbench();
    reg reset_;
    
    wire clock;
    clock_generator clk(
        .clock(clock)
    );

    wire out;

    // device under test
    out_n_clock dut(      
        .out(out),
        .clock(clock), .reset_(reset_)
    );

    initial begin
        $dumpfile("waveform.vcd");
        $dumpvars;

        reset_ = 0;
        #(2*clk.HALF_PERIOD);
        reset_ = 1;

        #(15*2*clk.HALF_PERIOD);

        $finish;
    end

endmodule

module clock_generator(
    clock
);
    output clock;

    parameter HALF_PERIOD = 5;

    reg CLOCK;
    assign clock = CLOCK;

    initial CLOCK <= 0;
    always #HALF_PERIOD CLOCK <= ~CLOCK;

endmodule

code/verilog/3/out_n_clock/waveform.vcd
$date
	Tue Nov 19 12:46:03 2024
$end
$version
	Icarus Verilog
$end
$timescale
	1s
$end
$scope module testbench $end
$var wire 1 ! out $end
$var wire 1 " clock $end
$var reg 1 # reset_ $end
$scope module clk $end
$var wire 1 " clock $end
$var reg 1 $ CLOCK $end
$upscope $end
$scope module dut $end
$var wire 1 " clock $end
$var wire 1 ! out $end
$var wire 1 # reset_ $end
$var wire 1 % next_star_s0 $end
$var wire 4 & next_count_s0 [3:0] $end
$var reg 4 ' COUNT [3:0] $end
$var reg 1 ( OUT $end
$var reg 1 ) STAR $end
$upscope $end
$upscope $end
$enddefinitions $end
#0
$dumpvars
0)
0(
b11 '
bx &
x%
0$
0#
0"
0!
$end
#2
b10 &
0%
#5
1"
1$
#10
0"
0$
1#
#15
1"
1$
#18
1!
1(
b10 '
#20
0"
0$
b1 &
#25
1"
1$
#28
b1 '
#30
0"
0$
1%
b0 &
#35
1"
1$
#38
1)
b0 '
#40
0"
0$
0%
b1111 &
#45
1"
1$
#48
0)
0!
0(
b11 '
#50
0"
0$
b10 &
#55
1"
1$
#58
1!
1(
b10 '
#60
0"
0$
b1 &
#65
1"
1$
#68
b1 '
#70
0"
0$
1%
b0 &
#75
1"
1$
#78
1)
b0 '
#80
0"
0$
0%
b1111 &
#85
1"
1$
#88
0)
0!
0(
b11 '
#90
0"
0$
b10 &
#95
1"
1$
#98
1!
1(
b10 '
#100
0"
0$
b1 &
#105
1"
1$
#108
b1 '
#110
0"
0$
1%
b0 &
#115
1"
1$
#118
1)
b0 '
#120
0"
0$
0%
b1111 &
#125
1"
1$
#128
0)
0!
0(
b11 '
#130
0"
0$
b10 &
#135
1"
1$
#138
1!
1(
b10 '
#140
0"
0$
b1 &
#145
1"
1$
#148
b1 '
#150
0"
0$
1%
b0 &
#155
1"
1$
#158
1)
b0 '
#160
0"
0$
0%
b1111 &
