assets/files/contatore-2-a719ac96e0a70849d9a8a8426da2f8bd.v
module contatore (
    out,
    clock, reset_
);
    output [2:0] out;
    input clock, reset_;

    reg [2:0] OUT;
    assign out = OUT;

    wire [2:0] next_out;
    assign #2 next_out = OUT + 1;

    always @(reset_ == 0) begin
        OUT <= 0;
    end

    always @(posedge clock) if (reset_ == 1) #3 begin
        OUT <= next_out;
    end
endmodule

code/verilog/3/contatore/testbench.v
module testbench();
    reg reset_;
    
    wire clock;
    clock_generator clk(
        .clock(clock)
    );

    wire [2:0] out;

    // device under test
    contatore dut(      
        .out(out),
        .clock(clock), .reset_(reset_)
    );

    initial begin
        $dumpfile("waveform.vcd");
        $dumpvars;

        reset_ = 0;
        #(2*clk.HALF_PERIOD);
        reset_ = 1;

        #(30*2*clk.HALF_PERIOD);

        $finish;
    end

endmodule

module clock_generator(
    clock
);
    output clock;

    parameter HALF_PERIOD = 5;

    reg CLOCK;
    assign clock = CLOCK;

    initial CLOCK <= 0;
    always #HALF_PERIOD CLOCK <= ~CLOCK;

endmodule

code/verilog/3/contatore/waveform.vcd
$date
	Tue Nov 19 12:00:50 2024
$end
$version
	Icarus Verilog
$end
$timescale
	1s
$end
$scope module testbench $end
$var wire 3 ! out [2:0] $end
$var wire 1 " clock $end
$var reg 1 # reset_ $end
$scope module clk $end
$var wire 1 " clock $end
$var reg 1 $ CLOCK $end
$upscope $end
$scope module dut $end
$var wire 1 " clock $end
$var wire 3 % out [2:0] $end
$var wire 1 # reset_ $end
$var wire 3 & next_out [2:0] $end
$var reg 3 ' OUT [2:0] $end
$upscope $end
$upscope $end
$enddefinitions $end
#0
$dumpvars
b0 '
bx &
b0 %
0$
0#
0"
b0 !
$end
#2
b1 &
#5
1"
1$
#10
0"
0$
1#
#15
1"
1$
#18
b1 !
b1 %
b1 '
#20
0"
0$
b10 &
#25
1"
1$
#28
b10 !
b10 %
b10 '
#30
0"
0$
b11 &
#35
1"
1$
#38
b11 !
b11 %
b11 '
#40
0"
0$
b100 &
#45
1"
1$
#48
b100 !
b100 %
b100 '
#50
0"
0$
b101 &
#55
1"
1$
#58
b101 !
b101 %
b101 '
#60
0"
0$
b110 &
#65
1"
1$
#68
b110 !
b110 %
b110 '
#70
0"
0$
b111 &
#75
1"
1$
#78
b111 !
b111 %
b111 '
#80
0"
0$
b0 &
#85
1"
1$
#88
b0 !
b0 %
b0 '
#90
0"
0$
b1 &
#95
1"
1$
#98
b1 !
b1 %
b1 '
#100
0"
0$
b10 &
#105
1"
1$
#108
b10 !
b10 %
b10 '
#110
0"
0$
b11 &
#115
1"
1$
#118
b11 !
b11 %
b11 '
#120
0"
0$
b100 &
#125
1"
1$
#128
b100 !
b100 %
b100 '
#130
0"
0$
b101 &
#135
1"
1$
#138
b101 !
b101 %
b101 '
#140
0"
0$
b110 &
#145
1"
1$
#148
b110 !
b110 %
b110 '
#150
0"
0$
b111 &
#155
1"
1$
#158
b111 !
b111 %
b111 '
#160
0"
0$
b0 &
#165
1"
1$
#168
b0 !
b0 %
b0 '
#170
0"
0$
b1 &
#175
1"
1$
#178
b1 !
b1 %
b1 '
#180
0"
0$
b10 &
#185
1"
1$
#188
b10 !
b10 %
b10 '
#190
0"
0$
b11 &
#195
1"
1$
#198
b11 !
b11 %
b11 '
#200
0"
0$
b100 &
#205
1"
1$
#208
b100 !
b100 %
b100 '
#210
0"
0$
b101 &
#215
1"
1$
#218
b101 !
b101 %
b101 '
#220
0"
0$
b110 &
#225
1"
1$
#228
b110 !
b110 %
b110 '
#230
0"
0$
b111 &
#235
1"
1$
#238
b111 !
b111 %
b111 '
#240
0"
0$
b0 &
#245
1"
1$
#248
b0 !
b0 %
b0 '
#250
0"
0$
b1 &
#255
1"
1$
#258
b1 !
b1 %
b1 '
#260
0"
0$
b10 &
#265
1"
1$
#268
b10 !
b10 %
b10 '
#270
0"
0$
b11 &
#275
1"
1$
#278
b11 !
b11 %
b11 '
#280
0"
0$
b100 &
#285
1"
1$
#288
b100 !
b100 %
b100 '
#290
0"
0$
b101 &
#295
1"
1$
#298
b101 !
b101 %
b101 '
#300
0"
0$
b110 &
#305
1"
1$
#308
b110 !
b110 %
b110 '
#310
0"
0$
b111 &
