assets/files/soluzione-8a02f0738f7d807eab3666ca2b5987e2.v
module ABC(
    a, b, p,
    dav_, rfd,
    clock, reset_
);
    input [3:0] a, b;
    output [5:0] p;

    input dav_;
    output rfd;

    input clock, reset_;

    reg [5:0] P;
    assign p = P;

    reg RFD;
    assign rfd = RFD;

    reg [3:0] A, B;

    wire [5:0] out_rc;
    PERIMETRO_RC rc(
        .a(A), .b(B),
        .p(out_rc)
    );

    reg [2:0] STAR;
    localparam 
        S0 = 0, 
        S1 = 1,
        S2 = 2, 
        S3 = 3;
    
    always @(reset_ == 0) begin
        RFD <= 1;
        P <= 0;
        STAR <= S0;
    end

    always @(posedge clock) if (reset_ == 1) #3 begin
        casex (STAR)
            S0: begin
                A <= a;
                B <= b;
                STAR <= (dav_ == 0) ? S1 : S0;
            end 

            S1: begin
                // P <= 2 * (A + B);
                P <= out_rc;
                STAR <= S2;           
            end  

            S2: begin
                RFD <= 0;
                STAR <= (dav_ == 1) ? S3 : S2;
            end

            S3: begin
                RFD <= 1;
                STAR <= S0;
            end
        endcase
    end

endmodule

module PERIMETRO_RC(
    a, b,
    p
);
    input [3:0] a, b;
    output [5:0] p;

    wire [4:0] somma;
    add #( .N(4) ) adder(
        .x(a), .y(b), .c_in(1'b0),
        .s(somma[3:0]), .c_out(somma[4])
    );

    assign p = { somma[3:0], 1'b0 };

endmodule

code/verilog/3/perimetro_rettangolo/testbench.v
module testbench();
    reg [3:0] a, b;
    reg reset_, dav_;

    wire clock, rfd;
    wire [5:0] p;

    clock_generator clk(
        .clock(clock)
    );

    ABC dut(
        .a(a), .b(b), .clock(clock), .reset_(reset_), .dav_(dav_),
        .p(p), .rfd(rfd)
    );

    // Debug variable, used to highlight points on the waveform
    reg error;

    initial begin
        $dumpfile("waveform.vcd");
        $dumpvars;

        //the following structure is used to wait for expected signals, and fail if too much time passes
        fork : f
            begin
                #100000;
                $display("Timeout - waiting for signal failed");
                disable f;
            end
        //actual tests start here
            begin
                //reset phase
                reset_ = 0; #(clk.HALF_PERIOD);
                dav_ = 1;
                reset_ = 1; #(clk.HALF_PERIOD);

                //clock e' all' edge negativo

                if(rfd != 1)
                    $display("rfd is not 1 after reset");
                    
                fork
                    begin: producer
                        reg [5:0] i;
                        reg [3:0] t_a, t_b;
                        reg [5:0] t_p;

                        for (i = 0; i < 32; i++) begin
                            {t_a, t_b, t_p}= get_testcase(i[4:0]);

                            #(2*clk.HALF_PERIOD);
                            a = t_a;
                            b = t_b;
                            #(2*clk.HALF_PERIOD);
                            dav_ = 0;

                            @(negedge rfd);
                            dav_ = 1; #1;
                            {a, b} = 8'bX;

                            @(posedge rfd);
                        end
                    end

                    begin: consumer
                        reg [5:0] i;
                        reg [3:0] t_a, t_b;
                        reg [5:0] t_p;

                        for (i = 0; i < 32; i++) begin
                            {t_a, t_b, t_p}= get_testcase(i[4:0]);

                            @(p);
                            if(p != t_p) begin
                                $display("Expected %d, received %d", t_p, p);
                                error = 1;
                            end
                        end
                    end
                join

                #10;
                disable f;
            end
        join

        $finish;
    end

    initial error = 0;
    always @(posedge error) #1
        error = 0;

    function automatic [13:0] get_testcase;
        input [4:0] i;

        reg [3:0] a, b;
        reg [5:0] p;

        begin
            a = i[4:1] + 3;
            b = i[3:0] + 1;
            p = 2 * (a + b);

            get_testcase = {a, b, p};
        end
    endfunction

endmodule

module clock_generator(
    clock
);
    output clock;

    parameter HALF_PERIOD = 5;

    reg CLOCK;
    assign clock = CLOCK;

    initial CLOCK <= 0;
    always #HALF_PERIOD CLOCK <= ~CLOCK;

endmodule

code/verilog/3/perimetro_rettangolo/reti_standard.v
// Sommatore valido sia per naturali che per interi, in base 2.
// Sia input che output sono a N cifre.
// Il circuito ha in uscita sia il carry che l'overflow, sta all'utilizzatore collegare quello corretto.
module add( 
    x, y, c_in,
    s, c_out, ow    
);
    parameter N = 2;

    input [N-1:0] x, y;
    input c_in;

    output [N-1:0] s;
    output c_out, ow;

    assign #1 {c_out, s} = x + y + c_in;
    assign #1 ow = (x[N-1] == y[N-1]) && (x[N-1] != s[N-1]);

endmodule

// Moltiplicatore con addizionatore per naturali in base 2.
// Moltiplicando (x) e addendo (c) a N bit, moltiplicatore (y) a M bit.
// Risultato (m) su N+M bit
module mul_add_nat(
    x, y, c,
    m
);

    parameter N = 2;
    parameter M = 2;

    input [N-1:0] x, c;
    input [M-1:0] y;

    output [N+M-1:0] m;

    assign #1 m = (x * y) + c;

endmodule

code/verilog/3/perimetro_rettangolo/waveform.vcd
$date
	Tue Nov 19 14:36:58 2024
$end
$version
	Icarus Verilog
$end
$timescale
	1s
$end
$scope module mul_add_nat $end
$var wire 2 ! c [1:0] $end
$var wire 2 " x [1:0] $end
$var wire 2 # y [1:0] $end
$var wire 4 $ m [3:0] $end
$upscope $end
$scope module testbench $end
$var wire 1 % rfd $end
$var wire 6 & p [5:0] $end
$var wire 1 ' clock $end
$var reg 4 ( a [3:0] $end
$var reg 4 ) b [3:0] $end
$var reg 1 * dav_ $end
$var reg 1 + error $end
$var reg 1 , reset_ $end
$scope function get_testcase $end
$upscope $end
$scope module clk $end
$var wire 1 ' clock $end
$var reg 1 - CLOCK $end
$upscope $end
$scope module dut $end
$var wire 4 . a [3:0] $end
$var wire 4 / b [3:0] $end
$var wire 1 ' clock $end
$var wire 1 * dav_ $end
$var wire 6 0 p [5:0] $end
$var wire 1 , reset_ $end
$var wire 1 % rfd $end
$var wire 6 1 out_rc [5:0] $end
$var reg 4 2 A [3:0] $end
$var reg 4 3 B [3:0] $end
$var reg 6 4 P [5:0] $end
$var reg 1 5 RFD $end
$var reg 3 6 STAR [2:0] $end
$scope module rc $end
$var wire 4 7 a [3:0] $end
$var wire 4 8 b [3:0] $end
$var wire 5 9 somma [4:0] $end
$var wire 6 : p [5:0] $end
$scope module adder $end
$var wire 1 ; c_in $end
$var wire 1 < ow $end
$var wire 4 = x [3:0] $end
$var wire 4 > y [3:0] $end
$var wire 4 ? s [3:0] $end
$var wire 1 @ c_out $end
$upscope $end
$upscope $end
$upscope $end
$scope fork f $end
$scope begin consumer $end
$var reg 6 A i [5:0] $end
$var reg 4 B t_a [3:0] $end
$var reg 4 C t_b [3:0] $end
$var reg 6 D t_p [5:0] $end
$upscope $end
$scope begin producer $end
$var reg 6 E i [5:0] $end
$var reg 4 F t_a [3:0] $end
$var reg 4 G t_b [3:0] $end
$var reg 6 H t_p [5:0] $end
$upscope $end
$upscope $end
$upscope $end
$enddefinitions $end
#0
$dumpvars
bx H
bx G
bx F
bx E
bx D
bx C
bx B
bx A
x@
bx ?
bx >
bx =
x<
0;
b0xxx00 :
bx 9
bx 8
bx 7
b0 6
15
b0 4
bx 3
bx 2
b0xxx00 1
b0 0
bx /
bx .
0-
0,
0+
x*
bx )
bx (
0'
b0 &
1%
bx $
bz #
bz "
bz !
$end
#5
1'
1-
1,
1*
#10
0'
0-
b11 F
b1 G
b1000 H
b0 E
b11 B
b1 C
b1000 D
b0 A
#15
1'
1-
#20
0'
0-
b1 )
b1 /
b11 (
b11 .
#25
1'
1-
#28
b1 3
b1 8
b1 >
b11 2
b11 7
b11 =
#29
b1000 1
b1000 :
b100 ?
b100 9
0@
#30
0'
0-
0<
0*
#35
1'
1-
#38
b1 6
#40
0'
0-
#45
1'
1-
#48
b10 C
b1010 D
b1 A
b10 6
b1000 &
b1000 0
b1000 4
#50
0'
0-
#55
1'
1-
#58
1*
0%
05
#59
bx (
bx .
bx )
bx /
#60
0'
0-
#65
1'
1-
#68
b11 6
#70
0'
0-
#75
1'
1-
#78
b10 G
b1010 H
b1 E
b0 6
1%
15
#80
0'
0-
#85
1'
1-
#88
b10 3
b10 8
b10 >
b10 )
b10 /
b11 (
b11 .
#89
b101 9
b101 ?
#90
0'
0-
#95
1'
1-
#98
b1 6
0*
#100
0'
0-
#105
1'
1-
#108
b10 6
#110
0'
0-
#115
1'
1-
#118
1*
0%
05
#119
bx (
bx .
bx )
bx /
#120
0'
0-
#125
1'
1-
#128
b11 6
#130
0'
0-
#135
1'
1-
#138
b100 F
b11 G
b1110 H
b10 E
b0 6
1%
15
#140
0'
0-
#145
1'
1-
#148
b11 3
b11 8
b11 >
b100 2
b100 7
b100 =
b11 )
b11 /
b100 (
b100 .
#149
b1100 1
b1100 :
b111 9
b111 ?
#150
0'
0-
#155
1'
1-
#158
b1 6
0*
#160
0'
0-
#165
1'
1-
#168
b100 B
b11 C
b1110 D
b10 A
1+
b10 6
b1100 &
b1100 0
b1100 4
#169
0+
#170
0'
0-
#175
1'
1-
#178
1*
0%
05
#179
bx (
bx .
bx )
bx /
#180
0'
0-
#185
1'
1-
#188
b11 6
#190
0'
0-
#195
1'
1-
#198
b100 G
b10000 H
b11 E
b0 6
1%
15
#200
0'
0-
#205
1'
1-
#208
b100 3
b100 8
b100 >
b100 )
b100 /
b100 (
b100 .
#209
b10000 1
b10000 :
b1000 9
b1000 ?
#210
0'
0-
1<
#215
1'
1-
#218
b1 6
0*
#220
0'
0-
#225
1'
1-
#228
b100 C
b10000 D
b11 A
1+
b10 6
b10000 &
b10000 0
b10000 4
#229
0+
#230
0'
0-
#235
1'
1-
#238
1*
0%
05
#239
bx (
bx .
bx )
bx /
#240
0'
0-
#245
1'
1-
#248
b11 6
#250
0'
0-
#255
1'
1-
#258
b101 F
b101 G
b10100 H
b100 E
b0 6
1%
15
#260
0'
0-
#265
1'
1-
#268
b101 3
b101 8
b101 >
b101 2
b101 7
b101 =
b101 )
b101 /
b101 (
b101 .
#269
b10100 1
b10100 :
b1010 9
b1010 ?
#270
0'
0-
#275
1'
1-
#278
b1 6
0*
#280
0'
0-
#285
1'
1-
#288
b101 B
b101 C
b10100 D
b100 A
1+
b10 6
b10100 &
b10100 0
b10100 4
#289
0+
#290
0'
0-
#295
1'
1-
#298
1*
0%
05
#299
bx (
bx .
bx )
bx /
#300
0'
0-
#305
1'
1-
#308
b11 6
#310
0'
0-
#315
1'
1-
#318
b110 G
b10110 H
b101 E
b0 6
1%
15
#320
0'
0-
#325
1'
1-
#328
b110 3
b110 8
b110 >
b110 )
b110 /
b101 (
b101 .
#329
b1011 9
b1011 ?
#330
0'
0-
#335
1'
1-
#338
b1 6
0*
#340
0'
0-
#345
1'
1-
#348
b10 6
#350
0'
0-
#355
1'
1-
#358
1*
0%
05
#359
bx (
bx .
bx )
bx /
#360
0'
0-
#365
1'
1-
#368
b11 6
#370
0'
0-
#375
1'
1-
#378
b110 F
b111 G
b11010 H
b110 E
b0 6
1%
15
#380
0'
0-
#385
1'
1-
#388
b111 3
b111 8
b111 >
b110 2
b110 7
b110 =
b111 )
b111 /
b110 (
b110 .
#389
b11000 1
b11000 :
b1101 9
b1101 ?
#390
0'
0-
#395
1'
1-
#398
b1 6
0*
#400
0'
0-
#405
1'
1-
#408
b110 C
b10110 D
b101 A
1+
b10 6
b11000 &
b11000 0
b11000 4
#409
0+
#410
0'
0-
#415
1'
1-
#418
1*
0%
05
#419
bx (
bx .
bx )
bx /
#420
0'
0-
#425
1'
1-
#428
b11 6
#430
0'
0-
#435
1'
1-
#438
b1000 G
b11100 H
b111 E
b0 6
1%
15
#440
0'
0-
#445
1'
1-
#448
b1000 3
b1000 8
b1000 >
b1000 )
b1000 /
b110 (
b110 .
#449
b11100 1
b11100 :
b1110 9
b1110 ?
0<
#450
0'
0-
#455
1'
1-
#458
b1 6
0*
#460
0'
0-
#465
1'
1-
#468
b110 B
b111 C
b11010 D
b110 A
1+
b10 6
b11100 &
b11100 0
b11100 4
#469
0+
#470
0'
0-
#475
1'
1-
#478
1*
0%
05
#479
bx (
bx .
bx )
bx /
#480
0'
0-
#485
1'
1-
#488
b11 6
#490
0'
0-
#495
1'
1-
#498
b111 F
b1001 G
b100000 H
b1000 E
b0 6
1%
15
#500
0'
0-
#505
1'
1-
#508
b1001 3
b1001 8
b1001 >
b111 2
b111 7
b111 =
b1001 )
b1001 /
b111 (
b111 .
#509
b0 1
b0 :
b0 ?
b10000 9
1@
#510
0'
0-
#515
1'
1-
#518
b1 6
0*
#520
0'
0-
#525
1'
1-
#528
b1000 C
b11100 D
b111 A
1+
b10 6
b0 &
b0 0
b0 4
#529
0+
#530
0'
0-
#535
1'
1-
#538
1*
0%
05
#539
bx (
bx .
bx )
bx /
#540
0'
0-
#545
1'
1-
#548
b11 6
#550
0'
0-
#555
1'
1-
#558
b1010 G
b100010 H
b1001 E
b0 6
1%
15
#560
0'
0-
#565
1'
1-
#568
b1010 3
b1010 8
b1010 >
b1010 )
b1010 /
b111 (
b111 .
#569
b10001 9
b1 ?
#570
0'
0-
#575
1'
1-
#578
b1 6
0*
#580
0'
0-
#585
1'
1-
#588
b10 6
#590
0'
0-
#595
1'
1-
#598
1*
0%
05
#599
bx (
bx .
bx )
bx /
#600
0'
0-
#605
1'
1-
#608
b11 6
#610
0'
0-
#615
1'
1-
#618
b1000 F
b1011 G
b100110 H
b1010 E
b0 6
1%
15
#620
0'
0-
#625
1'
1-
#628
b1011 3
b1011 8
b1011 >
b1000 2
b1000 7
b1000 =
b1011 )
b1011 /
b1000 (
b1000 .
#629
b100 1
b100 :
b10011 9
b11 ?
1<
#630
0'
0-
#635
1'
1-
#638
b1 6
0*
#640
0'
0-
#645
1'
1-
#648
b111 B
b1001 C
b100000 D
b1000 A
1+
b10 6
b100 &
b100 0
b100 4
#649
0+
#650
0'
0-
#655
1'
1-
#658
1*
0%
05
#659
bx (
bx .
bx )
bx /
#660
0'
0-
#665
1'
1-
#668
b11 6
#670
0'
0-
#675
1'
1-
#678
b1100 G
b101000 H
b1011 E
b0 6
1%
15
#680
0'
0-
#685
1'
1-
#688
b1100 3
b1100 8
b1100 >
b1100 )
b1100 /
b1000 (
b1000 .
#689
b1000 1
b1000 :
b10100 9
b100 ?
#690
0'
0-
#695
1'
1-
#698
b1 6
0*
#700
0'
0-
#705
1'
1-
#708
b1010 C
b100010 D
b1001 A
1+
b10 6
b1000 &
b1000 0
b1000 4
#709
0+
#710
0'
0-
#715
1'
1-
#718
1*
0%
05
#719
bx (
bx .
bx )
bx /
#720
0'
0-
#725
1'
1-
#728
b11 6
#730
0'
0-
#735
1'
1-
#738
b1001 F
b1101 G
b101100 H
b1100 E
b0 6
1%
15
#740
0'
0-
#745
1'
1-
#748
b1101 3
b1101 8
b1101 >
b1001 2
b1001 7
b1001 =
b1101 )
b1101 /
b1001 (
b1001 .
#749
b1100 1
b1100 :
b10110 9
b110 ?
#750
0'
0-
#755
1'
1-
#758
b1 6
0*
#760
0'
0-
#765
1'
1-
#768
b1000 B
b1011 C
b100110 D
b1010 A
1+
b10 6
b1100 &
b1100 0
b1100 4
#769
0+
#770
0'
0-
#775
1'
1-
#778
1*
0%
05
#779
bx (
bx .
bx )
bx /
#780
0'
0-
#785
1'
1-
#788
b11 6
#790
0'
0-
#795
1'
1-
#798
b1110 G
b101110 H
b1101 E
b0 6
1%
15
#800
0'
0-
#805
1'
1-
#808
b1110 3
b1110 8
b1110 >
b1110 )
b1110 /
b1001 (
b1001 .
#809
b10111 9
b111 ?
#810
0'
0-
#815
1'
1-
#818
b1 6
0*
#820
0'
0-
#825
1'
1-
#828
b10 6
#830
0'
0-
#835
1'
1-
#838
1*
0%
05
#839
bx (
bx .
bx )
bx /
#840
0'
0-
#845
1'
1-
#848
b11 6
#850
0'
0-
#855
1'
1-
#858
b1010 F
b1111 G
b110010 H
b1110 E
b0 6
1%
15
#860
0'
0-
#865
1'
1-
#868
b1111 3
b1111 8
b1111 >
b1010 2
b1010 7
b1010 =
b1111 )
b1111 /
b1010 (
b1010 .
#869
b10000 1
b10000 :
b11001 9
b1001 ?
#870
0'
0-
0<
#875
1'
1-
#878
b1 6
0*
#880
0'
0-
#885
1'
1-
#888
b1100 C
b101000 D
b1011 A
1+
b10 6
b10000 &
b10000 0
b10000 4
#889
0+
#890
0'
0-
#895
1'
1-
#898
1*
0%
05
#899
bx (
bx .
bx )
bx /
#900
0'
0-
#905
1'
1-
#908
b11 6
#910
0'
0-
#915
1'
1-
#918
b0 G
b10100 H
b1111 E
b0 6
1%
15
#920
0'
0-
#925
1'
1-
#928
b0 3
b0 8
b0 >
b0 )
b0 /
b1010 (
b1010 .
#929
b10100 1
b10100 :
b1010 ?
b1010 9
0@
#930
0'
0-
#935
1'
1-
#938
b1 6
0*
#940
0'
0-
#945
1'
1-
#948
b1001 B
b1101 C
b101100 D
b1100 A
1+
b10 6
b10100 &
b10100 0
b10100 4
#949
0+
#950
0'
0-
#955
1'
1-
#958
1*
0%
05
#959
bx (
bx .
bx )
bx /
#960
0'
0-
#965
1'
1-
#968
b11 6
#970
0'
0-
#975
1'
1-
#978
b1011 F
b1 G
b11000 H
b10000 E
b0 6
1%
15
#980
0'
0-
#985
1'
1-
#988
b1 3
b1 8
b1 >
b1011 2
b1011 7
b1011 =
b1 )
b1 /
b1011 (
b1011 .
#989
b11000 1
b11000 :
b1100 9
b1100 ?
#990
0'
0-
#995
1'
1-
#998
b1 6
0*
#1000
0'
0-
#1005
1'
1-
#1008
b1110 C
b101110 D
b1101 A
1+
b10 6
b11000 &
b11000 0
b11000 4
#1009
0+
#1010
0'
0-
#1015
1'
1-
#1018
1*
0%
05
#1019
bx (
bx .
bx )
bx /
#1020
0'
0-
#1025
1'
1-
#1028
b11 6
#1030
0'
0-
#1035
1'
1-
#1038
b10 G
b11010 H
b10001 E
b0 6
1%
15
#1040
0'
0-
#1045
1'
1-
#1048
b10 3
b10 8
b10 >
b10 )
b10 /
b1011 (
b1011 .
#1049
b1101 9
b1101 ?
#1050
0'
0-
#1055
1'
1-
#1058
b1 6
0*
#1060
0'
0-
#1065
1'
1-
#1068
b10 6
#1070
0'
0-
#1075
1'
1-
#1078
1*
0%
05
#1079
bx (
bx .
bx )
bx /
#1080
0'
0-
#1085
1'
1-
#1088
b11 6
#1090
0'
0-
#1095
1'
1-
#1098
b1100 F
b11 G
b11110 H
b10010 E
b0 6
1%
15
#1100
0'
0-
#1105
1'
1-
#1108
b11 3
b11 8
b11 >
b1100 2
b1100 7
b1100 =
b11 )
b11 /
b1100 (
b1100 .
#1109
b11100 1
b11100 :
b1111 9
b1111 ?
#1110
0'
0-
#1115
1'
1-
#1118
b1 6
0*
#1120
0'
0-
#1125
1'
1-
#1128
b1010 B
b1111 C
b110010 D
b1110 A
1+
b10 6
b11100 &
b11100 0
b11100 4
#1129
0+
#1130
0'
0-
#1135
1'
1-
#1138
1*
0%
05
#1139
bx (
bx .
bx )
bx /
#1140
0'
0-
#1145
1'
1-
#1148
b11 6
#1150
0'
0-
#1155
1'
1-
#1158
b100 G
b100000 H
b10011 E
b0 6
1%
15
#1160
0'
0-
#1165
1'
1-
#1168
b100 3
b100 8
b100 >
b100 )
b100 /
b1100 (
b1100 .
#1169
b0 1
b0 :
b0 ?
b10000 9
1@
#1170
0'
0-
#1175
1'
1-
#1178
b1 6
0*
#1180
0'
0-
#1185
1'
1-
#1188
b0 C
b10100 D
b1111 A
1+
b10 6
b0 &
b0 0
b0 4
#1189
0+
#1190
0'
0-
#1195
1'
1-
#1198
1*
0%
05
#1199
bx (
bx .
bx )
bx /
#1200
0'
0-
#1205
1'
1-
#1208
b11 6
#1210
0'
0-
#1215
1'
1-
#1218
b1101 F
b101 G
b100100 H
b10100 E
b0 6
1%
15
#1220
0'
0-
#1225
1'
1-
#1228
b101 3
b101 8
b101 >
b1101 2
b1101 7
b1101 =
b101 )
b101 /
b1101 (
b1101 .
#1229
b100 1
b100 :
b10010 9
b10 ?
#1230
0'
0-
#1235
1'
1-
#1238
b1 6
0*
#1240
0'
0-
#1245
1'
1-
#1248
b1011 B
b1 C
b11000 D
b10000 A
1+
b10 6
b100 &
b100 0
b100 4
#1249
0+
#1250
0'
0-
#1255
1'
1-
#1258
1*
0%
05
#1259
bx (
bx .
bx )
bx /
#1260
0'
0-
#1265
1'
1-
#1268
b11 6
#1270
0'
0-
#1275
1'
1-
#1278
b110 G
b100110 H
b10101 E
b0 6
1%
15
#1280
0'
0-
#1285
1'
1-
#1288
b110 3
b110 8
b110 >
b110 )
b110 /
b1101 (
b1101 .
#1289
b10011 9
b11 ?
#1290
0'
0-
#1295
1'
1-
#1298
b1 6
0*
#1300
0'
0-
#1305
1'
1-
#1308
b10 6
#1310
0'
0-
#1315
1'
1-
#1318
1*
0%
05
#1319
bx (
bx .
bx )
bx /
#1320
0'
0-
#1325
1'
1-
#1328
b11 6
#1330
0'
0-
#1335
1'
1-
#1338
b1110 F
b111 G
b101010 H
b10110 E
b0 6
1%
15
#1340
0'
0-
#1345
1'
1-
#1348
b111 3
b111 8
b111 >
b1110 2
b1110 7
b1110 =
b111 )
b111 /
b1110 (
b1110 .
#1349
b1000 1
b1000 :
b10101 9
b101 ?
#1350
0'
0-
#1355
1'
1-
#1358
b1 6
0*
#1360
0'
0-
#1365
1'
1-
#1368
b10 C
b11010 D
b10001 A
1+
b10 6
b1000 &
b1000 0
b1000 4
#1369
0+
#1370
0'
0-
#1375
1'
1-
#1378
1*
0%
05
#1379
bx (
bx .
bx )
bx /
#1380
0'
0-
#1385
1'
1-
#1388
b11 6
#1390
0'
0-
#1395
1'
1-
#1398
b1000 G
b101100 H
b10111 E
b0 6
1%
15
#1400
0'
0-
#1405
1'
1-
#1408
b1000 3
b1000 8
b1000 >
b1000 )
b1000 /
b1110 (
b1110 .
#1409
b1100 1
b1100 :
b10110 9
b110 ?
1<
#1410
0'
0-
#1415
1'
1-
#1418
b1 6
0*
#1420
0'
0-
#1425
1'
1-
#1428
b1100 B
b11 C
b11110 D
b10010 A
1+
b10 6
b1100 &
b1100 0
b1100 4
#1429
0+
#1430
0'
0-
#1435
1'
1-
#1438
1*
0%
05
#1439
bx (
bx .
bx )
bx /
#1440
0'
0-
#1445
1'
1-
#1448
b11 6
#1450
0'
0-
#1455
1'
1-
#1458
b1111 F
b1001 G
b110000 H
b11000 E
b0 6
1%
15
#1460
0'
0-
#1465
1'
1-
#1468
b1001 3
b1001 8
b1001 >
b1111 2
b1111 7
b1111 =
b1001 )
b1001 /
b1111 (
b1111 .
#1469
b10000 1
b10000 :
b11000 9
b1000 ?
#1470
0'
0-
0<
#1475
1'
1-
#1478
b1 6
0*
#1480
0'
0-
#1485
1'
1-
#1488
b100 C
b100000 D
b10011 A
1+
b10 6
b10000 &
b10000 0
b10000 4
#1489
0+
#1490
0'
0-
#1495
1'
1-
#1498
1*
0%
05
#1499
bx (
bx .
bx )
bx /
#1500
0'
0-
#1505
1'
1-
#1508
b11 6
#1510
0'
0-
#1515
1'
1-
#1518
b1010 G
b110010 H
b11001 E
b0 6
1%
15
#1520
0'
0-
#1525
1'
1-
#1528
b1010 3
b1010 8
b1010 >
b1010 )
b1010 /
b1111 (
b1111 .
#1529
b11001 9
b1001 ?
#1530
0'
0-
#1535
1'
1-
#1538
b1 6
0*
#1540
0'
0-
#1545
1'
1-
#1548
b10 6
#1550
0'
0-
#1555
1'
1-
#1558
1*
0%
05
#1559
bx (
bx .
bx )
bx /
#1560
0'
0-
#1565
1'
1-
#1568
b11 6
#1570
0'
0-
#1575
1'
1-
#1578
b0 F
b1011 G
b10110 H
b11010 E
b0 6
1%
15
#1580
0'
0-
#1585
1'
1-
#1588
b1011 3
b1011 8
b1011 >
b0 2
b0 7
b0 =
b1011 )
b1011 /
b0 (
b0 .
#1589
b10100 1
b10100 :
b1011 ?
b1011 9
0@
#1590
0'
0-
#1595
1'
1-
#1598
b1 6
0*
#1600
0'
0-
#1605
1'
1-
#1608
b1101 B
b101 C
b100100 D
b10100 A
1+
b10 6
b10100 &
b10100 0
b10100 4
#1609
0+
#1610
0'
0-
#1615
1'
1-
#1618
1*
0%
05
#1619
bx (
bx .
bx )
bx /
#1620
0'
0-
#1625
1'
1-
#1628
b11 6
#1630
0'
0-
#1635
1'
1-
#1638
b1100 G
b11000 H
b11011 E
b0 6
1%
15
#1640
0'
0-
#1645
1'
1-
#1648
b1100 3
b1100 8
b1100 >
b1100 )
b1100 /
b0 (
b0 .
#1649
b11000 1
b11000 :
b1100 9
b1100 ?
#1650
0'
0-
#1655
1'
1-
#1658
b1 6
0*
#1660
0'
0-
#1665
1'
1-
#1668
b110 C
b100110 D
b10101 A
1+
b10 6
b11000 &
b11000 0
b11000 4
#1669
0+
#1670
0'
0-
#1675
1'
1-
#1678
1*
0%
05
#1679
bx (
bx .
bx )
bx /
#1680
0'
0-
#1685
1'
1-
#1688
b11 6
#1690
0'
0-
#1695
1'
1-
#1698
b1 F
b1101 G
b11100 H
b11100 E
b0 6
1%
15
#1700
0'
0-
#1705
1'
1-
#1708
b1101 3
b1101 8
b1101 >
b1 2
b1 7
b1 =
b1101 )
b1101 /
b1 (
b1 .
#1709
b11100 1
b11100 :
b1110 9
b1110 ?
#1710
0'
0-
#1715
1'
1-
#1718
b1 6
0*
#1720
0'
0-
#1725
1'
1-
#1728
b1110 B
b111 C
b101010 D
b10110 A
1+
b10 6
b11100 &
b11100 0
b11100 4
#1729
0+
#1730
0'
0-
#1735
1'
1-
#1738
1*
0%
05
#1739
bx (
bx .
bx )
bx /
#1740
0'
0-
#1745
1'
1-
#1748
b11 6
#1750
0'
0-
#1755
1'
1-
#1758
b1110 G
b11110 H
b11101 E
b0 6
1%
15
#1760
0'
0-
#1765
1'
1-
#1768
b1110 3
b1110 8
b1110 >
b1110 )
b1110 /
b1 (
b1 .
#1769
b1111 9
b1111 ?
#1770
0'
0-
#1775
1'
1-
#1778
b1 6
0*
#1780
0'
0-
#1785
1'
1-
#1788
b10 6
#1790
0'
0-
#1795
1'
1-
#1798
1*
0%
05
#1799
bx (
bx .
bx )
bx /
#1800
0'
0-
#1805
1'
1-
#1808
b11 6
#1810
0'
0-
#1815
1'
1-
#1818
b10 F
b1111 G
b100010 H
b11110 E
b0 6
1%
15
#1820
0'
0-
#1825
1'
1-
#1828
b1111 3
b1111 8
b1111 >
b10 2
b10 7
b10 =
b1111 )
b1111 /
b10 (
b10 .
#1829
b0 1
b0 :
b1 ?
b10001 9
1@
#1830
0'
0-
#1835
1'
1-
#1838
b1 6
0*
#1840
0'
0-
#1845
1'
1-
#1848
b1000 C
b101100 D
b10111 A
1+
b10 6
b0 &
b0 0
b0 4
#1849
0+
#1850
0'
0-
#1855
1'
1-
#1858
1*
0%
05
#1859
bx (
bx .
bx )
bx /
#1860
0'
0-
#1865
1'
1-
#1868
b11 6
#1870
0'
0-
#1875
1'
1-
#1878
b0 G
b100 H
b11111 E
b0 6
1%
15
#1880
0'
0-
#1885
1'
1-
#1888
b0 3
b0 8
b0 >
b0 )
b0 /
b10 (
b10 .
#1889
b100 1
b100 :
b10 ?
b10 9
0@
#1890
0'
0-
#1895
1'
1-
#1898
b1 6
0*
#1900
0'
0-
#1905
1'
1-
#1908
b1111 B
b1001 C
b110000 D
b11000 A
1+
b10 6
b100 &
b100 0
b100 4
#1909
0+
#1910
0'
0-
#1915
1'
1-
#1918
1*
0%
05
#1919
bx (
bx .
bx )
bx /
#1920
0'
0-
#1925
1'
1-
#1928
b11 6
#1930
0'
0-
#1935
1'
1-
#1938
b100000 E
b0 6
1%
15
#1940
0'
0-
#1945
1'
1-
#1948
bx 3
bx 8
bx >
bx 2
bx 7
bx =
#1949
b0xxx00 1
b0xxx00 :
bx ?
bx 9
x@
x<
